echopy/__init__.py
echopy/echo.py
echopy/transaction.py
echopy/echoapi/__init__.py
echopy/echoapi/ws/__init__.py
echopy/echoapi/ws/echoapi.py
echopy/echoapi/ws/exceptions.py
echopy/echoapi/ws/reconnectionwebsocket.py
echopy/echoapi/ws/rpc.py
echopy/echoapi/ws/simplewebsocket.py
echopy/echoapi/ws_api/__init__.py
echopy/echoapi/ws_api/asset_api.py
echopy/echoapi/ws_api/database_api.py
echopy/echoapi/ws_api/did_api.py
echopy/echoapi/ws_api/history_api.py
echopy/echoapi/ws_api/login_api.py
echopy/echoapi/ws_api/network_api.py
echopy/echoapi/ws_api/registration_api.py
echopy/echobase/__init__.py
echopy/echobase/account.py
echopy/echobase/base58.py
echopy/echobase/bip39_dictionary.py
echopy/echobase/crypto.py
echopy/echobase/feetypes.py
echopy/echobase/objects.py
echopy/echobase/objecttypes.py
echopy/echobase/operationids.py
echopy/echobase/operations.py
echopy/echobase/prefix.py
echopy/echobase/types.py
echopy/echobase/utils.py
echopy/echobase/validation.py
echopy/echobase/config/__init__.py
echopy/echobase/config/api_config.py
echopy/echobase/config/chain_config.py
echopy/echobase/config/implementation_object_types.py
echopy/echobase/config/object_types.py
echopy/echobase/config/operations_ids.py
echopy/echobase/config/reserved_spaces.py
echopy/echobase/config/ws_constants.py
echopy_lib-0.1.73.dist-info/LICENSE.txt
echopy_lib-0.1.73.dist-info/METADATA
echopy_lib-0.1.73.dist-info/WHEEL
echopy_lib-0.1.73.dist-info/top_level.txt
echopy_lib-0.1.73.dist-info/RECORD
