Metadata-Version: 2.1
Name: echopy-lib
Version: 0.1.73
Summary: Python library for ECHO blockchain.
Home-page: https://echo-dev.io/
Author: PixelPlex inc
Author-email: dev@pixelplex.io
License: MIT
Download-URL: https://pypi.python.org/pypi/echopy-lib
Keywords: echo,blockchain,api,rpc
Platform: UNKNOWN
Classifier: License :: OSI Approved :: MIT License
Classifier: Operating System :: OS Independent
Classifier: Programming Language :: Python :: 3
Classifier: Programming Language :: Python :: 3.5
Classifier: Programming Language :: Python :: 3.6
Classifier: Programming Language :: Python :: 3.7
Classifier: Development Status :: 4 - Beta
Classifier: Intended Audience :: Developers
Requires-Dist: appdirs
Requires-Dist: dateutils
Requires-Dist: ecdsa
Requires-Dist: iroha
Requires-Dist: numpy
Requires-Dist: pycryptodome
Requires-Dist: pylibscrypt
Requires-Dist: pyyaml
Requires-Dist: requests
Requires-Dist: websocket-client
